{"skeleton":{"hash":"kZdbcjFFDGETpfL/nfbGXyCdNkI","spine":"3.8.99","x":-1482.16,"y":-164.94,"width":1900,"height":750},"bones":[{"name":"root"},{"name":"xiangxiang","parent":"root","x":-0.75,"y":-30.11},{"name":"zuo","parent":"xiangxiang","length":12.43,"rotation":163.75,"x":-0.61,"y":48.31},{"name":"you","parent":"xiangxiang","length":12.08,"rotation":40.97,"x":3.49,"y":48.42},{"name":"xian","parent":"xiangxiang","length":10,"rotation":-37.41,"x":4.49,"y":47.3},{"name":"paipai","parent":"xian","length":5.36,"rotation":-3.69,"x":9.83,"y":-0.19},{"name":"X","parent":"root"},{"name":"X2","parent":"root","x":511.96,"y":26.22}],"slots":[{"name":"tb","bone":"xiangxiang","attachment":"tb","blend":"additive"},{"name":"tb2","bone":"xiangxiang","attachment":"tb","blend":"additive"},{"name":"xiangxiang","bone":"xiangxiang","attachment":"tb/lihe"},{"name":"you","bone":"you","attachment":"tb/you"},{"name":"zhongjian","bone":"xiangxiang","attachment":"tb/zhongjian"},{"name":"zuo","bone":"zuo","attachment":"tb/zuo"},{"name":"xian","bone":"xian","attachment":"tb/xian"},{"name":"paipai","bone":"paipai","attachment":"tb/paipai"},{"name":"xin","bone":"X"},{"name":"xin2","bone":"X2"}],"skins":[{"name":"default","attachments":{"paipai":{"tb/paipai":{"x":12.13,"y":-0.12,"rotation":41.1,"width":31,"height":30}},"tb":{"tb":{"x":0.75,"y":30.11,"scaleX":0.98,"scaleY":0.98,"width":84,"height":83}},"tb2":{"tb":{"x":0.75,"y":30.11,"scaleX":0.98,"scaleY":0.98,"width":84,"height":83}},"xian":{"tb/xian":{"x":4.04,"y":-1.55,"rotation":37.41,"width":16,"height":13}},"xiangxiang":{"tb/lihe":{"x":0.25,"y":27.11,"width":69,"height":64}},"xin":{"xin":{"x":0.5,"y":0.5,"width":37,"height":37}},"xin2":{"xin":{"x":0.5,"y":0.5,"width":37,"height":37}},"you":{"tb/you":{"x":10.57,"y":0.34,"rotation":-40.97,"width":23,"height":19}},"zhongjian":{"tb/zhongjian":{"x":3.75,"y":46.11,"width":8,"height":8}},"zuo":{"tb/zuo":{"x":10.37,"y":0.63,"rotation":-163.75,"width":27,"height":23}}}}],"animations":{"daiji":{"slots":{"tb":{"color":[{"color":"ffffff00"}]},"tb2":{"color":[{"color":"ffffff00"}]},"xin":{"color":[{"color":"ffffff00"}],"attachment":[{"name":"xin"}]}},"bones":{"X":{"translate":[{"x":-27.03,"y":-18.88}],"scale":[{"x":0.255,"y":0.255}]},"xian":{"rotate":[{},{"time":1,"angle":9.21},{"time":2}]},"paipai":{"rotate":[{"angle":2.15},{"time":0.2333},{"time":1.2333,"angle":9.21},{"time":2,"angle":2.15}]}}},"lingqu":{"slots":{"tb":{"color":[{"color":"ffffff2e"},{"time":0.3333,"color":"ffffff93"},{"time":1,"color":"ffffff2e"},{"time":1.3333,"color":"ffffff93"},{"time":2,"color":"ffffff2e"}]},"tb2":{"color":[{"color":"ffffff09"},{"time":0.3333,"color":"ffffff2c"},{"time":1,"color":"ffffff09"},{"time":1.3333,"color":"ffffff2c"},{"time":2,"color":"ffffff09"}]},"xin":{"color":[{"color":"ffffff00","curve":"stepped"},{"time":0.0333,"color":"ffffff00"},{"time":0.2667,"color":"ffffffff"},{"time":0.5333,"color":"ffffff00","curve":"stepped"},{"time":0.7,"color":"ffffff00"},{"time":0.9667,"color":"ffffffff"},{"time":1.2667,"color":"ffffff00","curve":"stepped"},{"time":1.4667,"color":"ffffff00"},{"time":1.6667,"color":"ffffffff"},{"time":1.9,"color":"ffffff00"}],"attachment":[{"name":"xin"}]},"xin2":{"color":[{"color":"ffffffff"},{"time":0.2333,"color":"ffffff00","curve":"stepped"},{"time":0.3333,"color":"ffffff00"},{"time":0.5333,"color":"ffffffff"},{"time":0.8,"color":"ffffff00","curve":"stepped"},{"time":1,"color":"ffffff00"},{"time":1.2,"color":"ffffffff"},{"time":1.4333,"color":"ffffff00","curve":"stepped"},{"time":1.8,"color":"ffffff00"},{"time":2,"color":"ffffffff"}],"attachment":[{"name":"xin"}]}},"bones":{"zuo":{"rotate":[{},{"time":0.2667,"angle":4.39},{"time":0.5,"angle":0.3},{"time":0.7667,"angle":7.51},{"time":1},{"time":1.2667,"angle":4.39},{"time":1.5,"angle":0.3},{"time":1.7667,"angle":7.51},{"time":2}],"scale":[{},{"time":0.2667,"x":0.981},{"time":0.5,"x":1.013},{"time":0.7667,"x":0.995},{"time":1},{"time":1.2667,"x":0.981},{"time":1.5,"x":1.013},{"time":1.7667,"x":0.995},{"time":2}]},"you":{"rotate":[{},{"time":0.2667,"angle":-2.84},{"time":0.5,"angle":1.76},{"time":0.7667,"angle":-4.02},{"time":1},{"time":1.2667,"angle":-2.84},{"time":1.5,"angle":1.76},{"time":1.7667,"angle":-4.02},{"time":2}],"scale":[{},{"time":0.2667,"x":0.99},{"time":0.5,"x":1.012},{"time":0.7667,"x":0.992},{"time":1},{"time":1.2667,"x":0.99},{"time":1.5,"x":1.012},{"time":1.7667,"x":0.992},{"time":2}]},"xian":{"rotate":[{},{"time":0.1667,"angle":17.88},{"time":0.2667,"angle":5.95},{"time":0.3333,"angle":22.13},{"time":0.4,"angle":12.15},{"time":0.5333,"angle":19.31},{"time":1},{"time":1.1667,"angle":17.88},{"time":1.2667,"angle":5.95},{"time":1.3333,"angle":22.13},{"time":1.4,"angle":12.15},{"time":1.5333,"angle":19.31},{"time":1.8333}]},"paipai":{"rotate":[{},{"time":0.2333,"angle":9.59},{"time":0.3333,"angle":3.29},{"time":0.4,"angle":10.06},{"time":0.4667,"angle":2.28},{"time":0.6,"angle":12.18},{"time":1},{"time":1.2333,"angle":9.59},{"time":1.3333,"angle":3.29},{"time":1.4,"angle":10.06},{"time":1.4667,"angle":2.28},{"time":1.6,"angle":12.18},{"time":1.9}]},"xiangxiang":{"rotate":[{},{"time":0.0667,"angle":1.86},{"time":0.1333,"angle":-2.06},{"time":0.2,"angle":1.86},{"time":0.2667,"angle":-2.06},{"time":0.3333,"angle":1.86},{"time":1},{"time":1.0667,"angle":1.86},{"time":1.1333,"angle":-2.06},{"time":1.2,"angle":1.86},{"time":1.2667,"angle":-2.06},{"time":1.3333,"angle":1.86},{"time":2}],"scale":[{},{"time":0.3333,"x":0.99,"y":1.02},{"time":1,"x":1.02,"y":0.99},{"time":1.3333,"x":0.99,"y":1.02},{"time":2}]},"X":{"translate":[{"curve":0,"c2":0.62,"c3":0.663,"c4":0.99},{"time":0.0333,"x":-35.36,"y":21.02,"curve":"stepped"},{"time":0.5333,"x":-35.36,"y":21.02,"curve":0.322,"c2":0.63,"c3":0.731,"c4":0.98},{"time":0.7,"x":23.36,"y":-5.39,"curve":"stepped"},{"time":1.2667,"x":23.36,"y":-5.39,"curve":0.366,"c2":0.63,"c3":0.721,"c4":0.97},{"time":1.4667,"x":-27.03,"y":-18.88}],"scale":[{"x":0.255,"y":0.255,"curve":"stepped"},{"time":0.0333,"x":0.255,"y":0.255},{"time":0.2667,"x":0.615,"y":0.615},{"time":0.5333,"x":0.255,"y":0.255,"curve":"stepped"},{"time":0.7,"x":0.255,"y":0.255},{"time":0.9667,"x":0.615,"y":0.615},{"time":1.2667,"x":0.255,"y":0.255,"curve":"stepped"},{"time":1.4667,"x":0.255,"y":0.255},{"time":1.6667,"x":0.615,"y":0.615},{"time":1.9,"x":0.255,"y":0.255}]},"X2":{"translate":[{"x":-483.85,"y":-26.45,"curve":"stepped"},{"time":0.2333,"x":-483.85,"y":-26.45,"curve":0.354,"c2":0.58,"c3":0.689,"c4":0.92},{"time":0.3333,"x":-498.66,"y":-46.14,"curve":"stepped"},{"time":0.8,"x":-498.66,"y":-46.14,"curve":0.366,"c2":0.63,"c3":0.722,"c4":0.97},{"time":1,"x":-542.09,"y":-14.13,"curve":"stepped"},{"time":1.4333,"x":-542.09,"y":-14.13,"curve":0.363,"c2":0.61,"c3":0.702,"c4":0.95},{"time":1.8,"x":-483.85,"y":-26.45}],"scale":[{"x":0.255,"y":0.255,"curve":"stepped"},{"time":0.3333,"x":0.255,"y":0.255},{"time":0.5333,"x":0.615,"y":0.615},{"time":0.8,"x":0.255,"y":0.255,"curve":"stepped"},{"time":1,"x":0.255,"y":0.255},{"time":1.2,"x":0.615,"y":0.615},{"time":1.4333,"x":0.255,"y":0.255}]}}}}}